mirrorearth_sdk/Aggregation.py
mirrorearth_sdk/Model.py
mirrorearth_sdk/Unit.py
mirrorearth_sdk/Variable.py
mirrorearth_sdk/VariableWithValues.py
mirrorearth_sdk/VariablesWithTime.py
mirrorearth_sdk/WeatherApiResponse.py
mirrorearth_sdk/__init__.py
mirrorearth_sdk/demo.py
mirrorearth_sdk/hisroty_vars.py
mirrorearth_sdk/parse.py
mirrorearth_sdk/variable_mapping.py
mirrorearth_sdk-0.1.0.dist-info/licenses/LICENSE
mirrorearth_sdk-0.1.0.dist-info/METADATA
mirrorearth_sdk-0.1.0.dist-info/WHEEL
mirrorearth_sdk-0.1.0.dist-info/top_level.txt
mirrorearth_sdk-0.1.0.dist-info/RECORD
