Metadata-Version: 2.4
Name: mirrorearth_sdk
Version: 0.1.0
Summary: Python SDK for MirrorEarth Weather API
Home-page: https://open.mirror-earth.com/docs/get-started/1-start
Author: MirrorEarth
Author-email: MirrorEarth <info@mirrorearth.com>
License: MIT
Project-URL: Homepage, https://open.mirror-earth.com/docs/get-started/1-start
Project-URL: Repository, https://open.mirror-earth.com/docs/get-started/1-start
Classifier: Development Status :: 4 - Beta
Classifier: Intended Audience :: Developers
Classifier: Programming Language :: Python :: 3
Classifier: Programming Language :: Python :: 3.8
Classifier: Programming Language :: Python :: 3.9
Classifier: Programming Language :: Python :: 3.10
Classifier: Programming Language :: Python :: 3.11
Classifier: License :: OSI Approved :: MIT License
Classifier: Operating System :: OS Independent
Requires-Python: >=3.8
License-File: LICENSE
Requires-Dist: numpy
Requires-Dist: pandas
Requires-Dist: flatbuffers
Requires-Dist: requests
Dynamic: author
Dynamic: home-page
Dynamic: license-file
Dynamic: requires-python
